object_detector/__init__.py
object_detector/downloader.py
object_detector/object_detector.py
object_detector-1.9.data/scripts/objectdetector
object_detector-1.9.dist-info/METADATA
object_detector-1.9.dist-info/WHEEL
object_detector-1.9.dist-info/top_level.txt
object_detector-1.9.dist-info/RECORD
