Metadata-Version: 2.1
Name: object-detector
Version: 1.9
Summary: Using this library you can detect objects from a video, images, with few lines of code
Home-page: https://github.com/ujjwalkar0/object_detector
Author: Ujjwal Kar
Author-email: ujjwalkar21@gmail.com
License: UNKNOWN
Keywords: YoLo,Object Detector,Artificial Intelligence
Platform: UNKNOWN
Classifier: Programming Language :: Python :: 3
Classifier: Operating System :: Unix
Classifier: Operating System :: MacOS :: MacOS X
Classifier: Operating System :: Microsoft :: Windows
Requires-Python: >=3.6
Requires-Dist: Pillow (==9.1.0)
Requires-Dist: numpy (==1.22.3)
Requires-Dist: opencv-python (==4.5.5.64)
Requires-Dist: packaging (==21.3)
Requires-Dist: pyparsing (==3.0.9)
Requires-Dist: pytesseract (==0.3.9)
